SimpleLinestring/__init__.py
SimpleLinestring/postprocess.cpython-310-x86_64-linux-gnu.so
SimpleLinestring/preprocess.cpython-310-x86_64-linux-gnu.so
simplelinestring-0.1.8.dist-info/licenses/LICENSE
simplelinestring-0.1.8.dist-info/METADATA
simplelinestring-0.1.8.dist-info/WHEEL
simplelinestring-0.1.8.dist-info/top_level.txt
simplelinestring-0.1.8.dist-info/RECORD
