Metadata-Version: 2.4
Name: SimpleLinestring
Version: 0.1.8
Home-page: https://github.com/
Author: Chiliades
Author-email: chiliades.com@gmail.com
License: GPL license
Requires-Python: ==3.10.8
License-File: LICENSE
Requires-Dist: torch==2.6.0
Requires-Dist: networkx==3.4.2
Requires-Dist: shapely==2.0.7
Requires-Dist: numpy==2.2.4
Requires-Dist: scikit-learn==1.6.1
Requires-Dist: pandas==2.2.3
Requires-Dist: scipy==1.15.2
Requires-Dist: statsmodels==0.14.5
Dynamic: author
Dynamic: author-email
Dynamic: home-page
Dynamic: license
Dynamic: license-file
Dynamic: requires-dist
Dynamic: requires-python
